excelcolumnizer/__init__.py
excelcolumnizer/_excelColumnizer.py
excelcolumnizer-0.0.9.dist-info/METADATA
excelcolumnizer-0.0.9.dist-info/WHEEL
excelcolumnizer-0.0.9.dist-info/licenses/LICENSE.txt
excelcolumnizer-0.0.9.dist-info/RECORD
